rwth_colors.py
rwth_CD_colors-0.1.1.dist-info/METADATA
rwth_CD_colors-0.1.1.dist-info/WHEEL
rwth_CD_colors-0.1.1.dist-info/top_level.txt
rwth_CD_colors-0.1.1.dist-info/RECORD
