Metadata-Version: 2.1
Name: rwth-CD-colors
Version: 0.1.1
Summary: Provider for RWTH colormap aliases
Home-page: 
Author: Thomas Offergeld
Author-email: t.offergeld@iaew.rwth-aachen.de
License: MIT
Platform: UNKNOWN
